setup.py
tv/__init__.py
tv/cli.py
tv.egg-info/PKG-INFO
tv.egg-info/SOURCES.txt
tv.egg-info/dependency_links.txt
tv.egg-info/entry_points.txt
tv.egg-info/not-zip-safe
tv.egg-info/requires.txt
tv.egg-info/top_level.txt