Metadata-Version: 1.0
Name: tv
Version: 0.1
Summary: tv: text view images in your console using true color and unicode 9.0 characters
Home-page: http://github.com/daleroberts/tv
Author: Dale Roberts
Author-email: dale.o.roberts@gmail.com
License: MIT
Platform: UNKNOWN
